<?xml version="1.0" encoding="utf-8"?>
<!--from odoo import models, fields, api
from datetime import date, datetime -->
<odoo>
    <data noupdate="1">
        <record id="gnuhealth_test_type_ultrasound" model="imaging.test.type">
            <field name="code">US</field>
            <field name="name">Ultrasound</field>
        </record>
        <record id="gnuhealth_test_type_mri" model="imaging.test.type">
            <field name="code">MRI</field>
            <field name="name">MRI</field>
        </record>
        <record id="gnuhealth_test_type_xray" model="imaging.test.type">
            <field name="code">XR</field>
            <field name="name">X-ray</field>
        </record>
        <record id="gnuhealth_test_type_ctscan" model="imaging.test.type">
            <field name="code">CT</field>
            <field name="name">CT Scan</field>
        </record>
        <record id="gnuhealth_test_type_petscan" model="imaging.test.type">
            <field name="code">PET</field>
            <field name="name">PET Scan</field>
        </record>
        <!-- categorias de productos -->
        <!--record id="product_category_1" model="product.category">
           <field name="parent_id" ref="product_category_all"/>
           <field name="name">Imaging Services</field>
       </record-->
        <!--record id="product_template_ultrasoundcharges" model="product.template">
            <field name="name">Ultrasound charges</field>
            <field name="type">service</field>
            <field name="categ_id">3</field>
        </record>
        <record id="product_template_mricharges" model="product.template">
            <field name="name">MRI charges</field>
        </record>
        <record id="product_template_xraycharges" model="product.template">
            <field name="name">X-ray charges</field>
        </record>
        <record id="product_template_ctscancharges" model="product.template">
            <field name="name">CT Scan charges</field>
        </record>
        <record id="product_template_petscancharges" model="product.template">
            <field name="name">PET Scan charges</field>
        </record-->
    </data>
</odoo>
